icloud_email/__init__.py
icloud_email-2.0.0.dist-info/METADATA
icloud_email-2.0.0.dist-info/WHEEL
icloud_email-2.0.0.dist-info/licenses/LICENSE
icloud_email-2.0.0.dist-info/RECORD
