Metadata-Version: 2.3
Name: icloud-email
Version: 2.0.0
Summary: Simple utility for sending emails via iCloud.
Project-URL: Homepage, https://github.com/mizuki-hikaru/icloud-email
Project-URL: Issues, https://github.com/mizuki-hikaru/icloud-email/issues
Author-email: Mizuki Hikaru <mizuki@hikaru.org>
License-File: LICENSE
Classifier: License :: OSI Approved :: MIT License
Classifier: Operating System :: OS Independent
Classifier: Programming Language :: Python :: 3
Requires-Python: >=3.9
